[
  {
    "doctype": "Property Setter",
    "name": "Sales Invoice-atcud_code-read_only",
    "property": "read_only",
    "property_type": "Check",
    "doc_type": "Sales Invoice",
    "doctype_or_field": "DocField",
    "field_name": "atcud_code",
    "value": "1",
    "default_value": null,
    "is_system_generated": 0,
    "for_doctype": "Sales Invoice"
  },
  {
    "doctype": "Property Setter",
    "name": "Sales Invoice-atcud_code-description",
    "property": "description",
    "property_type": "Text",
    "doc_type": "Sales Invoice",
    "doctype_or_field": "DocField",
    "field_name": "atcud_code",
    "value": "Código Único de Documento (ATCUD) - Gerado automaticamente conforme Portaria 195/2020",
    "default_value": null,
    "is_system_generated": 0,
    "for_doctype": "Sales Invoice"
  },
  {
    "doctype": "Property Setter",
    "name": "POS Invoice-atcud_code-read_only",
    "property": "read_only",
    "property_type": "Check",
    "doc_type": "POS Invoice",
    "doctype_or_field": "DocField",
    "field_name": "atcud_code",
    "value": "1",
    "default_value": null,
    "is_system_generated": 0,
    "for_doctype": "POS Invoice"
  },
  {
    "doctype": "Property Setter",
    "name": "Purchase Invoice-atcud_code-read_only",
    "property": "read_only",
    "property_type": "Check",
    "doc_type": "Purchase Invoice",
    "doctype_or_field": "DocField",
    "field_name": "atcud_code",
    "value": "1",
    "default_value": null,
    "is_system_generated": 0,
    "for_doctype": "Purchase Invoice"
  },
  {
    "doctype": "Property Setter",
    "name": "Payment Entry-atcud_code-read_only",
    "property": "read_only",
    "property_type": "Check",
    "doc_type": "Payment Entry",
    "doctype_or_field": "DocField",
    "field_name": "atcud_code",
    "value": "1",
    "default_value": null,
    "is_system_generated": 0,
    "for_doctype": "Payment Entry"
  },
  {
    "doctype": "Property Setter",
    "name": "Company-portugal_compliance_enabled-default",
    "property": "default",
    "property_type": "Check",
    "doc_type": "Company",
    "doctype_or_field": "DocField",
    "field_name": "portugal_compliance_enabled",
    "value": "0",
    "default_value": null,
    "is_system_generated": 0,
    "for_doctype": "Company"
  }
]
